{"_id":{"$oid":"5f78e5b08325e51dac8761a9"},"product_id":"1","product_name":"Jacket","lead_time":"5","weight_gsm":"300","quantity":"6","price_rs":"500","buyer_name":"Seema"}
{"_id":{"$oid":"5f78e5b08325e51dac8761aa"},"product_id":"2","product_name":"Sweater","lead_time":"3","weight_gsm":"250","quantity":"3","price_rs":"1000","buyer_name":"Seema"}
{"_id":{"$oid":"5f78e5b08325e51dac8761ab"},"product_id":"3","product_name":"Blazer","lead_time":"1","weight_gsm":"350","quantity":"4","price_rs":"5500","buyer_name":"Seema"}
{"_id":{"$oid":"5f78e5b08325e51dac8761ac"},"product_id":"4","product_name":"Sweater","lead_time":"6","weight_gsm":"350","quantity":"5","price_rs":"2500","buyer_name":"Seema"}
{"_id":{"$oid":"5f78e5b08325e51dac8761ad"},"product_id":"5","product_name":"Trousers","lead_time":"10","weight_gsm":"200","quantity":"5","price_rs":"4500","buyer_name":"Seema"}
{"_id":{"$oid":"5f78e5b08325e51dac8761ae"},"product_id":"6","product_name":"T-Shirts","lead_time":"1","weight_gsm":"300","quantity":"2","price_rs":"4500","buyer_name":"Seema"}
{"_id":{"$oid":"5f78e5b08325e51dac8761af"},"product_id":"7","product_name":"Skirt","lead_time":"3","weight_gsm":"150","quantity":"6","price_rs":"7000","buyer_name":"Seema"}
{"_id":{"$oid":"5f78e5b08325e51dac8761b0"},"product_id":"8","product_name":"Raincoat","lead_time":"8","weight_gsm":"50","quantity":"1","price_rs":"5500","buyer_name":"Seema"}
{"_id":{"$oid":"5f78e5b08325e51dac8761b1"},"product_id":"9","product_name":"Blazer","lead_time":"10","weight_gsm":"200","quantity":"1","price_rs":"1500","buyer_name":"Seema"}
{"_id":{"$oid":"5f78e5b08325e51dac8761b2"},"product_id":"10","product_name":"Blazer","lead_time":"6","weight_gsm":"200","quantity":"6","price_rs":"2000","buyer_name":"Seema"}
{"_id":{"$oid":"5f78e5b08325e51dac8761b3"},"product_id":"11","product_name":"Blazer","lead_time":"6","weight_gsm":"50","quantity":"5","price_rs":"1000","buyer_name":"Seema"}
{"_id":{"$oid":"5f78e5b08325e51dac8761b4"},"product_id":"12","product_name":"Short","lead_time":"8","weight_gsm":"200","quantity":"3","price_rs":"1000","buyer_name":"Seema"}
{"_id":{"$oid":"5f78e5b08325e51dac8761b5"},"product_id":"13","product_name":"Trousers","lead_time":"8","weight_gsm":"200","quantity":"4","price_rs":"7000","buyer_name":"Seema"}
{"_id":{"$oid":"5f78e5b08325e51dac8761b6"},"product_id":"14","product_name":"Blazer","lead_time":"7","weight_gsm":"200","quantity":"4","price_rs":"1000","buyer_name":"Seema"}
{"_id":{"$oid":"5f78e5b08325e51dac8761b7"},"product_id":"15","product_name":"Dress","lead_time":"8","weight_gsm":"50","quantity":"4","price_rs":"4500","buyer_name":"Seema"}
{"_id":{"$oid":"5f78e5b08325e51dac8761b8"},"product_id":"16","product_name":"Trousers","lead_time":"7","weight_gsm":"250","quantity":"4","price_rs":"500","buyer_name":"Seema"}
{"_id":{"$oid":"5f78e5b08325e51dac8761b9"},"product_id":"17","product_name":"Blazer","lead_time":"4","weight_gsm":"200","quantity":"3","price_rs":"2000","buyer_name":"Seema"}
{"_id":{"$oid":"5f78e5b08325e51dac8761ba"},"product_id":"18","product_name":"Jeans","lead_time":"7","weight_gsm":"150","quantity":"6","price_rs":"5500","buyer_name":"Seema"}
{"_id":{"$oid":"5f78e5b08325e51dac8761bb"},"product_id":"19","product_name":"Skirt","lead_time":"6","weight_gsm":"200","quantity":"3","price_rs":"1000","buyer_name":"Seema"}
{"_id":{"$oid":"5f78e5b08325e51dac8761bc"},"product_id":"20","product_name":"Blazer","lead_time":"3","weight_gsm":"200","quantity":"4","price_rs":"500","buyer_name":"Seema"}
{"_id":{"$oid":"5f78e5b08325e51dac8761bd"},"product_id":"21","product_name":"Skirt","lead_time":"4","weight_gsm":"300","quantity":"4","price_rs":"2000","buyer_name":"Karan"}
{"_id":{"$oid":"5f78e5b08325e51dac8761be"},"product_id":"22","product_name":"Short","lead_time":"4","weight_gsm":"100","quantity":"2","price_rs":"7000","buyer_name":"Karan"}
{"_id":{"$oid":"5f78e5b08325e51dac8761bf"},"product_id":"23","product_name":"Sweater","lead_time":"15","weight_gsm":"200","quantity":"5","price_rs":"1000","buyer_name":"Karan"}
{"_id":{"$oid":"5f78e5b08325e51dac8761c0"},"product_id":"24","product_name":"T-Shirts","lead_time":"1","weight_gsm":"50","quantity":"4","price_rs":"4500","buyer_name":"Karan"}
{"_id":{"$oid":"5f78e5b08325e51dac8761c1"},"product_id":"25","product_name":"Jeans","lead_time":"4","weight_gsm":"300","quantity":"6","price_rs":"1000","buyer_name":"Karan"}
{"_id":{"$oid":"5f78e5b08325e51dac8761c2"},"product_id":"26","product_name":"Sweater","lead_time":"7","weight_gsm":"300","quantity":"5","price_rs":"10000","buyer_name":"Karan"}
{"_id":{"$oid":"5f78e5b08325e51dac8761c3"},"product_id":"27","product_name":"Short","lead_time":"2","weight_gsm":"200","quantity":"5","price_rs":"2500","buyer_name":"Karan"}
{"_id":{"$oid":"5f78e5b08325e51dac8761c4"},"product_id":"28","product_name":"Blazer","lead_time":"2","weight_gsm":"150","quantity":"3","price_rs":"10000","buyer_name":"Karan"}
{"_id":{"$oid":"5f78e5b08325e51dac8761c5"},"product_id":"29","product_name":"Trousers","lead_time":"9","weight_gsm":"350","quantity":"2","price_rs":"5500","buyer_name":"Karan"}
{"_id":{"$oid":"5f78e5b08325e51dac8761c6"},"product_id":"30","product_name":"Trousers","lead_time":"9","weight_gsm":"250","quantity":"3","price_rs":"7000","buyer_name":"Karan"}
{"_id":{"$oid":"5f78e5b08325e51dac8761c7"},"product_id":"31","product_name":"Jacket","lead_time":"7","weight_gsm":"50","quantity":"6","price_rs":"2000","buyer_name":"Karan"}
{"_id":{"$oid":"5f78e5b08325e51dac8761c8"},"product_id":"32","product_name":"Jeans","lead_time":"2","weight_gsm":"300","quantity":"2","price_rs":"7000","buyer_name":"Karan"}
{"_id":{"$oid":"5f78e5b08325e51dac8761c9"},"product_id":"33","product_name":"Raincoat","lead_time":"5","weight_gsm":"200","quantity":"3","price_rs":"10000","buyer_name":"Karan"}
{"_id":{"$oid":"5f78e5b08325e51dac8761ca"},"product_id":"34","product_name":"Jacket","lead_time":"6","weight_gsm":"150","quantity":"4","price_rs":"1000","buyer_name":"Karan"}
{"_id":{"$oid":"5f78e5b08325e51dac8761cb"},"product_id":"35","product_name":"Sweater","lead_time":"2","weight_gsm":"150","quantity":"4","price_rs":"7000","buyer_name":"Karan"}
{"_id":{"$oid":"5f78e5b08325e51dac8761cc"},"product_id":"36","product_name":"Short","lead_time":"8","weight_gsm":"150","quantity":"3","price_rs":"5500","buyer_name":"Karan"}
{"_id":{"$oid":"5f78e5b08325e51dac8761cd"},"product_id":"37","product_name":"Raincoat","lead_time":"8","weight_gsm":"100","quantity":"1","price_rs":"4500","buyer_name":"Karan"}
{"_id":{"$oid":"5f78e5b08325e51dac8761ce"},"product_id":"38","product_name":"Trousers","lead_time":"5","weight_gsm":"250","quantity":"3","price_rs":"2500","buyer_name":"Karan"}
{"_id":{"$oid":"5f78e5b08325e51dac8761cf"},"product_id":"39","product_name":"T-Shirts","lead_time":"10","weight_gsm":"150","quantity":"2","price_rs":"10000","buyer_name":"Karan"}
{"_id":{"$oid":"5f78e5b08325e51dac8761d0"},"product_id":"40","product_name":"Jeans","lead_time":"9","weight_gsm":"350","quantity":"5","price_rs":"1000","buyer_name":"Karan"}
{"_id":{"$oid":"5f78e5b08325e51dac8761d1"},"product_id":"41","product_name":"Sweater","lead_time":"1","weight_gsm":"300","quantity":"3","price_rs":"1500","buyer_name":"Michael"}
{"_id":{"$oid":"5f78e5b08325e51dac8761d2"},"product_id":"42","product_name":"Skirt","lead_time":"3","weight_gsm":"350","quantity":"3","price_rs":"2500","buyer_name":"Michael"}
{"_id":{"$oid":"5f78e5b08325e51dac8761d3"},"product_id":"43","product_name":"Sweater","lead_time":"5","weight_gsm":"250","quantity":"5","price_rs":"1000","buyer_name":"Michael"}
{"_id":{"$oid":"5f78e5b08325e51dac8761d4"},"product_id":"44","product_name":"Dress","lead_time":"5","weight_gsm":"300","quantity":"4","price_rs":"500","buyer_name":"Michael"}
{"_id":{"$oid":"5f78e5b08325e51dac8761d5"},"product_id":"45","product_name":"Sweater","lead_time":"2","weight_gsm":"350","quantity":"2","price_rs":"2000","buyer_name":"Michael"}
{"_id":{"$oid":"5f78e5b08325e51dac8761d6"},"product_id":"46","product_name":"Skirt","lead_time":"10","weight_gsm":"350","quantity":"5","price_rs":"1500","buyer_name":"Michael"}
{"_id":{"$oid":"5f78e5b08325e51dac8761d7"},"product_id":"47","product_name":"Trousers","lead_time":"8","weight_gsm":"200","quantity":"3","price_rs":"5500","buyer_name":"Michael"}
{"_id":{"$oid":"5f78e5b08325e51dac8761d8"},"product_id":"48","product_name":"T-Shirts","lead_time":"7","weight_gsm":"350","quantity":"4","price_rs":"1500","buyer_name":"Michael"}
{"_id":{"$oid":"5f78e5b08325e51dac8761d9"},"product_id":"49","product_name":"Short","lead_time":"9","weight_gsm":"200","quantity":"2","price_rs":"5500","buyer_name":"Michael"}
{"_id":{"$oid":"5f78e5b08325e51dac8761da"},"product_id":"50","product_name":"Dress","lead_time":"1","weight_gsm":"200","quantity":"2","price_rs":"7000","buyer_name":"Michael"}
{"_id":{"$oid":"5f78e5b08325e51dac8761db"},"product_id":"51","product_name":"Short","lead_time":"5","weight_gsm":"100","quantity":"1","price_rs":"10000","buyer_name":"Michael"}
{"_id":{"$oid":"5f78e5b08325e51dac8761dc"},"product_id":"52","product_name":"Raincoat","lead_time":"1","weight_gsm":"200","quantity":"6","price_rs":"500","buyer_name":"Michael"}
{"_id":{"$oid":"5f78e5b08325e51dac8761dd"},"product_id":"53","product_name":"Raincoat","lead_time":"2","weight_gsm":"350","quantity":"4","price_rs":"500","buyer_name":"Michael"}
{"_id":{"$oid":"5f78e5b08325e51dac8761de"},"product_id":"54","product_name":"Blazer","lead_time":"1","weight_gsm":"250","quantity":"5","price_rs":"7000","buyer_name":"Michael"}
{"_id":{"$oid":"5f78e5b08325e51dac8761df"},"product_id":"55","product_name":"Blazer","lead_time":"8","weight_gsm":"100","quantity":"5","price_rs":"1500","buyer_name":"Michael"}
{"_id":{"$oid":"5f78e5b08325e51dac8761e0"},"product_id":"56","product_name":"Short","lead_time":"8","weight_gsm":"200","quantity":"3","price_rs":"1500","buyer_name":"Michael"}
{"_id":{"$oid":"5f78e5b08325e51dac8761e1"},"product_id":"57","product_name":"Raincoat","lead_time":"2","weight_gsm":"200","quantity":"5","price_rs":"1500","buyer_name":"Michael"}
{"_id":{"$oid":"5f78e5b08325e51dac8761e2"},"product_id":"58","product_name":"Jeans","lead_time":"7","weight_gsm":"300","quantity":"4","price_rs":"5500","buyer_name":"Michael"}
{"_id":{"$oid":"5f78e5b08325e51dac8761e3"},"product_id":"59","product_name":"Dress","lead_time":"10","weight_gsm":"150","quantity":"5","price_rs":"1500","buyer_name":"Michael"}
{"_id":{"$oid":"5f78e5b08325e51dac8761e4"},"product_id":"60","product_name":"Jeans","lead_time":"2","weight_gsm":"200","quantity":"5","price_rs":"1500","buyer_name":"Michael"}
{"_id":{"$oid":"5f78e5b08325e51dac8761e5"},"product_id":"61","product_name":"Jacket","lead_time":"10","weight_gsm":"50","quantity":"4","price_rs":"1500","buyer_name":"Rohit"}
{"_id":{"$oid":"5f78e5b08325e51dac8761e6"},"product_id":"62","product_name":"Jacket","lead_time":"17","weight_gsm":"150","quantity":"5","price_rs":"7000","buyer_name":"Rohit"}
{"_id":{"$oid":"5f78e5b08325e51dac8761e7"},"product_id":"63","product_name":"Short","lead_time":"2","weight_gsm":"200","quantity":"2","price_rs":"1500","buyer_name":"Rohit"}
{"_id":{"$oid":"5f78e5b08325e51dac8761e8"},"product_id":"64","product_name":"Raincoat","lead_time":"10","weight_gsm":"100","quantity":"2","price_rs":"2500","buyer_name":"Rohit"}
{"_id":{"$oid":"5f78e5b08325e51dac8761e9"},"product_id":"65","product_name":"Dress","lead_time":"9","weight_gsm":"100","quantity":"1","price_rs":"10000","buyer_name":"Rohit"}
{"_id":{"$oid":"5f78e5b08325e51dac8761ea"},"product_id":"66","product_name":"T-Shirts","lead_time":"7","weight_gsm":"150","quantity":"2","price_rs":"7000","buyer_name":"Rohit"}
{"_id":{"$oid":"5f78e5b08325e51dac8761eb"},"product_id":"67","product_name":"T-Shirts","lead_time":"7","weight_gsm":"200","quantity":"2","price_rs":"10000","buyer_name":"Rohit"}
{"_id":{"$oid":"5f78e5b08325e51dac8761ec"},"product_id":"68","product_name":"Raincoat","lead_time":"10","weight_gsm":"200","quantity":"5","price_rs":"10000","buyer_name":"Rohit"}
{"_id":{"$oid":"5f78e5b08325e51dac8761ed"},"product_id":"69","product_name":"Jeans","lead_time":"3","weight_gsm":"200","quantity":"6","price_rs":"1000","buyer_name":"Rohit"}
{"_id":{"$oid":"5f78e5b08325e51dac8761ee"},"product_id":"70","product_name":"T-Shirts","lead_time":"8","weight_gsm":"300","quantity":"6","price_rs":"1000","buyer_name":"Rohit"}
{"_id":{"$oid":"5f78e5b08325e51dac8761ef"},"product_id":"71","product_name":"Raincoat","lead_time":"4","weight_gsm":"300","quantity":"3","price_rs":"1000","buyer_name":"Rohit"}
{"_id":{"$oid":"5f78e5b08325e51dac8761f0"},"product_id":"72","product_name":"Jacket","lead_time":"12","weight_gsm":"150","quantity":"6","price_rs":"1500","buyer_name":"Rohit"}
{"_id":{"$oid":"5f78e5b08325e51dac8761f1"},"product_id":"73","product_name":"Short","lead_time":"8","weight_gsm":"200","quantity":"5","price_rs":"2000","buyer_name":"Rohit"}
{"_id":{"$oid":"5f78e5b08325e51dac8761f2"},"product_id":"74","product_name":"Short","lead_time":"10","weight_gsm":"100","quantity":"2","price_rs":"2000","buyer_name":"Rohit"}
{"_id":{"$oid":"5f78e5b08325e51dac8761f3"},"product_id":"75","product_name":"Trousers","lead_time":"7","weight_gsm":"150","quantity":"6","price_rs":"4500","buyer_name":"Rohit"}
{"_id":{"$oid":"5f78e5b08325e51dac8761f4"},"product_id":"76","product_name":"Sweater","lead_time":"2","weight_gsm":"250","quantity":"1","price_rs":"5500","buyer_name":"Rohit"}
{"_id":{"$oid":"5f78e5b08325e51dac8761f5"},"product_id":"77","product_name":"Trousers","lead_time":"3","weight_gsm":"150","quantity":"2","price_rs":"500","buyer_name":"Rohit"}
{"_id":{"$oid":"5f78e5b08325e51dac8761f6"},"product_id":"78","product_name":"Skirt","lead_time":"4","weight_gsm":"200","quantity":"1","price_rs":"2500","buyer_name":"Rohit"}
{"_id":{"$oid":"5f78e5b08325e51dac8761f7"},"product_id":"79","product_name":"Dress","lead_time":"10","weight_gsm":"350","quantity":"3","price_rs":"500","buyer_name":"Rohit"}
{"_id":{"$oid":"5f78e5b08325e51dac8761f8"},"product_id":"80","product_name":"Raincoat","lead_time":"5","weight_gsm":"150","quantity":"3","price_rs":"1000","buyer_name":"Rohit"}
{"_id":{"$oid":"5f78e5b08325e51dac8761f9"},"product_id":"81","product_name":"Jeans","lead_time":"5","weight_gsm":"50","quantity":"3","price_rs":"7000","buyer_name":"Garima"}
{"_id":{"$oid":"5f78e5b08325e51dac8761fa"},"product_id":"82","product_name":"Jacket","lead_time":"10","weight_gsm":"150","quantity":"4","price_rs":"4500","buyer_name":"Garima"}
{"_id":{"$oid":"5f78e5b08325e51dac8761fb"},"product_id":"83","product_name":"T-Shirts","lead_time":"9","weight_gsm":"50","quantity":"4","price_rs":"2500","buyer_name":"Garima"}
{"_id":{"$oid":"5f78e5b08325e51dac8761fc"},"product_id":"84","product_name":"Short","lead_time":"2","weight_gsm":"300","quantity":"3","price_rs":"10000","buyer_name":"Garima"}
{"_id":{"$oid":"5f78e5b08325e51dac8761fd"},"product_id":"85","product_name":"Jacket","lead_time":"6","weight_gsm":"350","quantity":"3","price_rs":"5500","buyer_name":"Garima"}
{"_id":{"$oid":"5f78e5b08325e51dac8761fe"},"product_id":"86","product_name":"Short","lead_time":"14","weight_gsm":"250","quantity":"4","price_rs":"1500","buyer_name":"Garima"}
{"_id":{"$oid":"5f78e5b08325e51dac8761ff"},"product_id":"87","product_name":"Jacket","lead_time":"10","weight_gsm":"250","quantity":"2","price_rs":"4500","buyer_name":"Garima"}
{"_id":{"$oid":"5f78e5b08325e51dac876200"},"product_id":"88","product_name":"Blazer","lead_time":"4","weight_gsm":"200","quantity":"1","price_rs":"10000","buyer_name":"Garima"}
{"_id":{"$oid":"5f78e5b08325e51dac876201"},"product_id":"89","product_name":"Jacket","lead_time":"7","weight_gsm":"150","quantity":"5","price_rs":"1000","buyer_name":"Garima"}
{"_id":{"$oid":"5f78e5b08325e51dac876202"},"product_id":"90","product_name":"Jacket","lead_time":"9","weight_gsm":"300","quantity":"3","price_rs":"2500","buyer_name":"Garima"}
{"_id":{"$oid":"5f78e5b08325e51dac876203"},"product_id":"91","product_name":"Dress","lead_time":"2","weight_gsm":"150","quantity":"5","price_rs":"4500","buyer_name":"Garima"}
{"_id":{"$oid":"5f78e5b08325e51dac876204"},"product_id":"92","product_name":"Raincoat","lead_time":"9","weight_gsm":"200","quantity":"4","price_rs":"1000","buyer_name":"Garima"}
{"_id":{"$oid":"5f78e5b08325e51dac876205"},"product_id":"93","product_name":"Short","lead_time":"9","weight_gsm":"150","quantity":"2","price_rs":"10000","buyer_name":"Garima"}
{"_id":{"$oid":"5f78e5b08325e51dac876206"},"product_id":"94","product_name":"Skirt","lead_time":"4","weight_gsm":"100","quantity":"1","price_rs":"1000","buyer_name":"Garima"}
{"_id":{"$oid":"5f78e5b08325e51dac876207"},"product_id":"95","product_name":"Blazer","lead_time":"6","weight_gsm":"250","quantity":"1","price_rs":"2000","buyer_name":"Garima"}
{"_id":{"$oid":"5f78e5b08325e51dac876208"},"product_id":"96","product_name":"Skirt","lead_time":"3","weight_gsm":"200","quantity":"6","price_rs":"1000","buyer_name":"Garima"}
{"_id":{"$oid":"5f78e5b08325e51dac876209"},"product_id":"97","product_name":"Dress","lead_time":"1","weight_gsm":"150","quantity":"3","price_rs":"10000","buyer_name":"Garima"}
{"_id":{"$oid":"5f78e5b08325e51dac87620a"},"product_id":"98","product_name":"Raincoat","lead_time":"4","weight_gsm":"250","quantity":"5","price_rs":"5500","buyer_name":"Garima"}
{"_id":{"$oid":"5f78e5b08325e51dac87620b"},"product_id":"99","product_name":"Sweater","lead_time":"6","weight_gsm":"150","quantity":"1","price_rs":"7000","buyer_name":"Garima"}
{"_id":{"$oid":"5f78e5b08325e51dac87620c"},"product_id":"100","product_name":"Sweater","lead_time":"11","weight_gsm":"200","quantity":"4","price_rs":"1000","buyer_name":"Garima"}
{"_id":{"$oid":"5f78e5b08325e51dac87620d"},"product_id":"","product_name":null,"lead_time":null,"weight_gsm":null,"quantity":null,"price_rs":null,"buyer_name":null}
